tmsyscall/__init__.py
tmsyscall/_sigsetops.py
tmsyscall/chroot.py
tmsyscall/eventfd.py
tmsyscall/inotify.py
tmsyscall/mount.py
tmsyscall/pivot_root.py
tmsyscall/signalfd.py
tmsyscall/sigprocmask.py
tmsyscall/unshare.py
tmsyscall/utils.py
tmsyscall-0.0.8.dist-info/DESCRIPTION.rst
tmsyscall-0.0.8.dist-info/METADATA
tmsyscall-0.0.8.dist-info/RECORD
tmsyscall-0.0.8.dist-info/WHEEL
tmsyscall-0.0.8.dist-info/entry_points.txt
tmsyscall-0.0.8.dist-info/metadata.json
tmsyscall-0.0.8.dist-info/top_level.txt
