Metadata-Version: 2.0
Name: tmsyscall
Version: 0.0.8
Summary: Python library for some advanced Linux system calls
Home-page: https://github.com/joaompinto/tmsyscall
Author: João Pinto
Author-email: lamego.pinto@gmail.com
License: UNKNOWN
Platform: UNKNOWN
Classifier: Development Status :: 1 - Planning
Classifier: Intended Audience :: Developers
Classifier: License :: Freely Distributable
Classifier: License :: OSI Approved :: Apache Software License
Classifier: Operating System :: OS Independent
Classifier: Programming Language :: Python :: 2.7
Classifier: Programming Language :: Python :: 3.4
